envtypes/__init__.py
test/__init__.py
test/test_envtypes.py
envtypes-0.3.1.dist-info/LICENCE.txt
envtypes-0.3.1.dist-info/METADATA
envtypes-0.3.1.dist-info/WHEEL
envtypes-0.3.1.dist-info/top_level.txt
envtypes-0.3.1.dist-info/RECORD
